CHANGELOG
LICENSE
MANIFEST.in
README.rst
setup.py
imaprelay/__init__.py
imaprelay/command.py
imaprelay/connection.py
imaprelay/relay.py
imaprelay/util.py
imaprelay.egg-info/PKG-INFO
imaprelay.egg-info/SOURCES.txt
imaprelay.egg-info/dependency_links.txt
imaprelay.egg-info/entry_points.txt
imaprelay.egg-info/top_level.txt