Metadata-Version: 1.0
Name: imaprelay
Version: 0.0.4
Summary: IMAP-to-SMTP relay: imaprelay relays messages from an IMAP INBOX to an SMTP server
Home-page: http://github.com/nickstenning/imaprelay
Author: Nick Stenning
Author-email: nick@whiteink.com
License: MIT
Platform: UNKNOWN
Classifier: Development Status :: 3 - Alpha
Classifier: Environment :: Console
Classifier: Intended Audience :: End Users/Desktop
Classifier: License :: OSI Approved :: MIT License
Classifier: Topic :: Communications :: Email
Classifier: Topic :: Communications :: Email :: Email Clients (MUA)
Classifier: Topic :: Communications :: Email :: Mail Transport Agents
Classifier: Topic :: Utilities
